{
  "seo": {
    "title": "オンラインZIP作成 - 無料ZIP圧縮ツール",
    "keywords": "ZIP作成, ZIP圧縮, オンラインアーカイバ, フォルダ圧縮",
    "description": "無料でオンラインでZIPファイルを作成。複数のファイルやフォルダをアップロードしてZIPにまとめます。高速、安全、ブラウザで完結。"
  },
  "hero": {
    "title": "無料オンラインZIP作成ツール",
    "subtitle": "複数のファイルやフォルダを瞬時にZIPアーカイブにまとめます。安全、高速、100%無料。"
  },
  "steps": [
    {
      "title": "アップロード",
      "desc": "ファイルやフォルダをここにドラッグ＆ドロップ。"
    },
    {
      "title": "設定",
      "desc": "ファイル名と圧縮レベルを設定。"
    },
    {
      "title": "ダウンロード",
      "desc": "ZIPを生成してすぐにダウンロード。"
    }
  ],
  "features": [
    {
      "title": "フォルダ対応",
      "desc": "フォルダ構造を維持したままアップロード可能。"
    },
    {
      "title": "ローカル処理",
      "desc": "ファイルはブラウザ内で処理され、サーバーには送信されません。"
    },
    {
      "title": "文字化け防止",
      "desc": "UTF-8エンコードを使用し、Windows/Macでの文字化けを防ぎます。"
    }
  ],
  "faq": [
    {
      "q": "フォルダをアップロードできますか？",
      "a": "はい、フォルダごとのアップロードに対応しています。ディレクトリ構造はZIPファイル内で維持されます。"
    },
    {
      "q": "WindowsやMacでファイル名が文字化けしますか？",
      "a": "いいえ、UTF-8エンコードを使用しているため、すべてのOSで正しく表示されます。"
    },
    {
      "q": "7z形式には対応していますか？",
      "a": "現在はZIP形式に対応しています。7z形式は近日対応予定です。"
    },
    {
      "q": "無料ですか？",
      "a": "はい、完全に無料です。隠れたコストはありません。"
    },
    {
      "q": "ファイルは安全ですか？",
      "a": "はい、すべての処理はブラウザ内で行われるため、デバイスから出ることはありません。"
    }
  ]
}